ap/motif/__init__.py
ap/motif/__version__.py
ap/motif/cli.py
ap/motif/utils.py
ap_motif-0.1.11.dist-info/LICENSE
ap_motif-0.1.11.dist-info/METADATA
ap_motif-0.1.11.dist-info/WHEEL
ap_motif-0.1.11.dist-info/entry_points.txt
ap_motif-0.1.11.dist-info/top_level.txt
ap_motif-0.1.11.dist-info/RECORD
