Metadata-Version: 2.1
Name: ap-motif
Version: 0.1.11
Summary: Motif is an opinionated templating toolkit built in Python.
Home-page: UNKNOWN
Author: Anna Poulakos
Author-email: anna.poulakos@gmail.com
License: MIT License
Platform: UNKNOWN
Classifier: Development Status :: 4 - Beta
Classifier: Intended Audience :: Developers
Classifier: License :: OSI Approved :: MIT License
Classifier: Programming Language :: Python
Classifier: Programming Language :: Python :: 3
Classifier: Programming Language :: Python :: 3.9
Requires-Python: >=3.8
